ovos_document_chunkers/__init__.py
ovos_document_chunkers/base.py
ovos_document_chunkers/version.py
ovos_document_chunkers/files/__init__.py
ovos_document_chunkers/files/doc.py
ovos_document_chunkers/files/docx.py
ovos_document_chunkers/files/markdown.py
ovos_document_chunkers/files/pdf.py
ovos_document_chunkers/files/webpages.py
ovos_document_chunkers/text/__init__.py
ovos_document_chunkers/text/paragraphs.py
ovos_document_chunkers/text/sentence.py
ovos_document_chunkers-0.1.1.dist-info/METADATA
ovos_document_chunkers-0.1.1.dist-info/WHEEL
ovos_document_chunkers-0.1.1.dist-info/top_level.txt
ovos_document_chunkers-0.1.1.dist-info/zip-safe
ovos_document_chunkers-0.1.1.dist-info/RECORD
