Metadata-Version: 2.1
Name: ovos-document-chunkers
Version: 0.1.1
Summary: A plugin for OVOS
Author: jarbasai
Author-email: jarbasai@mailfence.com
License: MIT
Keywords: OVOS openvoiceos plugin
Requires-Dist: quebra-frases
Requires-Dist: markdown-to-json
Requires-Dist: pysbd
Requires-Dist: wtpsplit
Requires-Dist: textract
